streamlit_extras/__init__.py
streamlit_extras/version.py
streamlit_extras/add_vertical_space/__init__.py
streamlit_extras/altex/__init__.py
streamlit_extras/annotated_text/__init__.py
streamlit_extras/app_logo/__init__.py
streamlit_extras/avatar/__init__.py
streamlit_extras/badges/__init__.py
streamlit_extras/bottom_container/__init__.py
streamlit_extras/button_selector/__init__.py
streamlit_extras/buy_me_a_coffee/__init__.py
streamlit_extras/camera_input_live/__init__.py
streamlit_extras/capture/__init__.py
streamlit_extras/card/__init__.py
streamlit_extras/chart_annotations/__init__.py
streamlit_extras/chart_container/__init__.py
streamlit_extras/colored_header/__init__.py
streamlit_extras/concurrency_limiter/__init__.py
streamlit_extras/customize_running/__init__.py
streamlit_extras/dataframe_explorer/__init__.py
streamlit_extras/echo_expander/__init__.py
streamlit_extras/embed_code/__init__.py
streamlit_extras/exception_handler/__init__.py
streamlit_extras/faker/__init__.py
streamlit_extras/floating_button/__init__.py
streamlit_extras/function_explorer/__init__.py
streamlit_extras/great_tables/__init__.py
streamlit_extras/grid/__init__.py
streamlit_extras/image_coordinates/__init__.py
streamlit_extras/image_in_tables/__init__.py
streamlit_extras/image_selector/__init__.py
streamlit_extras/jupyterlite/__init__.py
streamlit_extras/keyboard_text/__init__.py
streamlit_extras/keyboard_url/__init__.py
streamlit_extras/let_it_rain/__init__.py
streamlit_extras/mandatory_date_range/__init__.py
streamlit_extras/markdownlit/__init__.py
streamlit_extras/mention/__init__.py
streamlit_extras/metric_cards/__init__.py
streamlit_extras/no_default_selectbox/__init__.py
streamlit_extras/pdf_viewer/__init__.py
streamlit_extras/prometheus/__init__.py
streamlit_extras/prometheus/example/README.md
streamlit_extras/prometheus/example/app.py
streamlit_extras/prometheus/example/metrics.py
streamlit_extras/row/__init__.py
streamlit_extras/sandbox/__init__.py
streamlit_extras-0.7.7.dist-info/METADATA
streamlit_extras-0.7.7.dist-info/WHEEL
streamlit_extras-0.7.7.dist-info/licenses/LICENSE
streamlit_extras-0.7.7.dist-info/RECORD
